windowsget/__init__.py
windowsget/cli.py
windowsget/downloader.py
windowsget/logger.py
windowsget-0.0.9.dist-info/METADATA
windowsget-0.0.9.dist-info/WHEEL
windowsget-0.0.9.dist-info/entry_points.txt
windowsget-0.0.9.dist-info/top_level.txt
windowsget-0.0.9.dist-info/RECORD
